podcastbackup/__init__.py
podcastbackup/meta.py
podcastbackup/pb.py
podcastbackup-0.1.3.dist-info/LICENSE
podcastbackup-0.1.3.dist-info/METADATA
podcastbackup-0.1.3.dist-info/WHEEL
podcastbackup-0.1.3.dist-info/entry_points.txt
podcastbackup-0.1.3.dist-info/top_level.txt
podcastbackup-0.1.3.dist-info/RECORD
