Metadata-Version: 2.1
Name: podcastbackup
Version: 0.1.3
Summary: UNKNOWN
Home-page: https://github.com/duggan/podcastbackup
Author: Ross Duggan
Author-email: ross@duggan.ie
License: MIT License
Platform: UNKNOWN
Classifier: Development Status :: 4 - Beta
Classifier: Intended Audience :: Developers
Classifier: Natural Language :: English
Classifier: License :: OSI Approved :: MIT License
Classifier: Topic :: Internet :: WWW/HTTP
Classifier: Programming Language :: Python
Classifier: Programming Language :: Python :: 2.6
Classifier: Programming Language :: Python :: 2.7
Classifier: Programming Language :: Python :: 3.2
Classifier: Programming Language :: Python :: 3.3
Classifier: Programming Language :: Python :: Implementation :: PyPy
Requires-Dist: feedparser
Requires-Dist: requests
Requires-Dist: progressbar2
Requires-Dist: pypandoc
